loggertodb/__init__.py
loggertodb/cli.py
loggertodb/enhydris.py
loggertodb/exceptions.py
loggertodb/meteologgerstorage.py
loggertodb/upgrade.py
loggertodb-3.1.0.dist-info/LICENSE.rst
loggertodb-3.1.0.dist-info/METADATA
loggertodb-3.1.0.dist-info/WHEEL
loggertodb-3.1.0.dist-info/entry_points.txt
loggertodb-3.1.0.dist-info/top_level.txt
loggertodb-3.1.0.dist-info/RECORD
