Metadata-Version: 2.1
Name: loggertodb
Version: 3.1.0
Summary: Insert meteorological station data to Enhydris
Home-page: https://github.com/aptiko/loggertodb
Author: Antonis Christofides
Author-email: antonis@antonischristofides.com
License: GNU General Public License v3
Keywords: loggertodb
Classifier: Development Status :: 4 - Beta
Classifier: Intended Audience :: Developers
Classifier: License :: OSI Approved :: GNU General Public License v3 (GPLv3)
Classifier: Natural Language :: English
Classifier: Programming Language :: Python :: 3
Classifier: Programming Language :: Python :: 3.5
Classifier: Programming Language :: Python :: 3.6
License-File: LICENSE.rst
Requires-Dist: Click (<9,>=7)
Requires-Dist: enhydris-api-client (<4,>=3)
Requires-Dist: iso8601
Requires-Dist: simpletail
Requires-Dist: tzdata
